sjfirebase/__init__.py
sjfirebase/jclass/__init__.py
sjfirebase/jclass/action.py
sjfirebase/jclass/database.py
sjfirebase/jclass/emailauth.py
sjfirebase/jclass/fieldvalue.py
sjfirebase/jclass/filter.py
sjfirebase/jclass/firestore.py
sjfirebase/jclass/function.py
sjfirebase/jclass/functions.py
sjfirebase/jclass/phoneauth.py
sjfirebase/jclass/servervalue.py
sjfirebase/jclass/storage.py
sjfirebase/jclass/transaction.py
sjfirebase/jclass/user.py
sjfirebase/jinterface/__init__.py
sjfirebase/jinterface/auth.py
sjfirebase/jinterface/database.py
sjfirebase/jinterface/firestore.py
sjfirebase/jinterface/phone.py
sjfirebase/jinterface/storage.py
sjfirebase/jinterface/task.py
sjfirebase/tools/__init__.py
sjfirebase/tools/mixin.py
sjfirebase/tools/serializer.py
sjfirebase-1.6.0.dist-info/LICENSE
sjfirebase-1.6.0.dist-info/METADATA
sjfirebase-1.6.0.dist-info/WHEEL
sjfirebase-1.6.0.dist-info/RECORD
